[
  {
    "id": "43904365",
    "Вакансия": "Программист Python",
    "Зарплата_нижний_порог": 60000.0,
    "Зарплата_верхний_порог": 200000.0,
    "Валюта": "руб.",
    "Ссылка": "https://nizhnekamsk.hh.ru/vacancy/43904365",
    "Сайт": "хехе.ру"
  },
  {
    "id": "43924184",
    "Вакансия": "Senior Data Scientist",
    "Зарплата_нижний_порог": 300000.0,
    "Зарплата_верхний_порог": 0.0,
    "Валюта": "руб.",
    "Ссылка": "https://nizhnekamsk.hh.ru/vacancy/43924184",
    "Сайт": "хехе.ру"
  },
  {
    "id": "43642994",
    "Вакансия": "Middle-backend Python разработчик / программист",
    "Зарплата_нижний_порог": 0.0,
    "Зарплата_верхний_порог": 150000.0,
    "Валюта": "руб.",
    "Ссылка": "https://nizhnekamsk.hh.ru/vacancy/43642994",
    "Сайт": "хехе.ру"
  },
  {
    "id": "43905874",
    "Вакансия": "Python developer/Data Engineer",
    "Зарплата_нижний_порог": 3000.0,
    "Зарплата_верхний_порог": 4000.0,
    "Валюта": "USD",
    "Ссылка": "https://nizhnekamsk.hh.ru/vacancy/43905874",
    "Сайт": "хехе.ру"
  },
  {
    "id": "43904231",
    "Вакансия": "Data Scientist",
    "Зарплата_нижний_порог": 60000.0,
    "Зарплата_верхний_порог": 200000.0,
    "Валюта": "руб.",
    "Ссылка": "https://nizhnekamsk.hh.ru/vacancy/43904231",
    "Сайт": "хехе.ру"
  },
  {
    "id": "43661969",
    "Вакансия": "Full-stack developer (Python middle) (Кипр)",
    "Зарплата_нижний_порог": 3200.0,
    "Зарплата_верхний_порог": 0.0,
    "Валюта": "EUR",
    "Ссылка": "https://nizhnekamsk.hh.ru/vacancy/43661969",
    "Сайт": "хехе.ру"
  },
  {
    "id": "43377259",
    "Вакансия": "Senior Python Developer",
    "Зарплата_нижний_порог": 200000.0,
    "Зарплата_верхний_порог": 250000.0,
    "Валюта": "руб.",
    "Ссылка": "https://nizhnekamsk.hh.ru/vacancy/43377259",
    "Сайт": "хехе.ру"
  },
  {
    "id": "43892687",
    "Вакансия": "Python Developer (Удалённо)",
    "Зарплата_нижний_порог": 60000.0,
    "Зарплата_верхний_порог": 100000.0,
    "Валюта": "руб.",
    "Ссылка": "https://nizhnekamsk.hh.ru/vacancy/43892687",
    "Сайт": "хехе.ру"
  },
  {
    "id": "43803674",
    "Вакансия": "Team Lead Python",
    "Зарплата_нижний_порог": 0.0,
    "Зарплата_верхний_порог": 0.0,
    "Валюта": 0,
    "Ссылка": "https://nizhnekamsk.hh.ru/vacancy/43803674",
    "Сайт": "хехе.ру"
  },
  {
    "id": "43784551",
    "Вакансия": "Разработчик Python",
    "Зарплата_нижний_порог": 0.0,
    "Зарплата_верхний_порог": 50000.0,
    "Валюта": "руб.",
    "Ссылка": "https://nizhnekamsk.hh.ru/vacancy/43784551",
    "Сайт": "хехе.ру"
  },
  {
    "id": "39388485",
    "Вакансия": "Senior Python Backend Developer (Machine Learning)",
    "Зарплата_нижний_порог": 250000.0,
    "Зарплата_верхний_порог": 350000.0,
    "Валюта": "руб.",
    "Ссылка": "https://nizhnekamsk.hh.ru/vacancy/39388485",
    "Сайт": "хехе.ру"
  },
  {
    "id": "39736489",
    "Вакансия": "Python-разработчик (Django, DRF)",
    "Зарплата_нижний_порог": 60000.0,
    "Зарплата_верхний_порог": 150000.0,
    "Валюта": "руб.",
    "Ссылка": "https://nizhnekamsk.hh.ru/vacancy/39736489",
    "Сайт": "хехе.ру"
  },
  {
    "id": "42684107",
    "Вакансия": "Junior разработчик Python (Django)",
    "Зарплата_нижний_порог": 40000.0,
    "Зарплата_верхний_порог": 60000.0,
    "Валюта": "руб.",
    "Ссылка": "https://nizhnekamsk.hh.ru/vacancy/42684107",
    "Сайт": "хехе.ру"
  },
  {
    "id": "43577231",
    "Вакансия": "Python-специалист",
    "Зарплата_нижний_порог": 70000.0,
    "Зарплата_верхний_порог": 90000.0,
    "Валюта": "руб.",
    "Ссылка": "https://nizhnekamsk.hh.ru/vacancy/43577231",
    "Сайт": "хехе.ру"
  },
  {
    "id": "43824278",
    "Вакансия": "Специалист по Data Science и Машинному Обучению",
    "Зарплата_нижний_порог": 300000.0,
    "Зарплата_верхний_порог": 0.0,
    "Валюта": "руб.",
    "Ссылка": "https://nizhnekamsk.hh.ru/vacancy/43824278",
    "Сайт": "хехе.ру"
  },
  {
    "id": "43961634",
    "Вакансия": "Junior Python Ingest developer",
    "Зарплата_нижний_порог": 0.0,
    "Зарплата_верхний_порог": 0.0,
    "Валюта": 0,
    "Ссылка": "https://nizhnekamsk.hh.ru/vacancy/43961634",
    "Сайт": "хехе.ру"
  },
  {
    "id": "43907208",
    "Вакансия": "Junior Data Engineer",
    "Зарплата_нижний_порог": 100000.0,
    "Зарплата_верхний_порог": 150000.0,
    "Валюта": "руб.",
    "Ссылка": "https://nizhnekamsk.hh.ru/vacancy/43907208",
    "Сайт": "хехе.ру"
  },
  {
    "id": "43723943",
    "Вакансия": "Junior Computer Vision Engineer",
    "Зарплата_нижний_порог": 80000.0,
    "Зарплата_верхний_порог": 150000.0,
    "Валюта": "руб.",
    "Ссылка": "https://nizhnekamsk.hh.ru/vacancy/43723943",
    "Сайт": "хехе.ру"
  },
  {
    "id": "42691024",
    "Вакансия": "Разработчик Python (Удалённая работа)",
    "Зарплата_нижний_порог": 0.0,
    "Зарплата_верхний_порог": 195000.0,
    "Валюта": "руб.",
    "Ссылка": "https://nizhnekamsk.hh.ru/vacancy/42691024",
    "Сайт": "хехе.ру"
  },
  {
    "id": "43242292",
    "Вакансия": "Разработчик-Python (Django, DRF)",
    "Зарплата_нижний_порог": 170000.0,
    "Зарплата_верхний_порог": 220000.0,
    "Валюта": "руб.",
    "Ссылка": "https://nizhnekamsk.hh.ru/vacancy/43242292",
    "Сайт": "хехе.ру"
  },
  {
    "id": "43628247",
    "Вакансия": "Разработчик Python (Django)",
    "Зарплата_нижний_порог": 100000.0,
    "Зарплата_верхний_порог": 160000.0,
    "Валюта": "руб.",
    "Ссылка": "https://nizhnekamsk.hh.ru/vacancy/43628247",
    "Сайт": "хехе.ру"
  },
  {
    "id": "43651376",
    "Вакансия": "Middle Python Developer",
    "Зарплата_нижний_порог": 240000.0,
    "Зарплата_верхний_порог": 0.0,
    "Валюта": "руб.",
    "Ссылка": "https://nizhnekamsk.hh.ru/vacancy/43651376",
    "Сайт": "хехе.ру"
  },
  {
    "id": "43371507",
    "Вакансия": "Golang/Python разработчик",
    "Зарплата_нижний_порог": 150000.0,
    "Зарплата_верхний_порог": 0.0,
    "Валюта": "руб.",
    "Ссылка": "https://nizhnekamsk.hh.ru/vacancy/43371507",
    "Сайт": "хехе.ру"
  },
  {
    "id": "43526714",
    "Вакансия": "Разработчик Python",
    "Зарплата_нижний_порог": 150000.0,
    "Зарплата_верхний_порог": 250000.0,
    "Валюта": "руб.",
    "Ссылка": "https://nizhnekamsk.hh.ru/vacancy/43526714",
    "Сайт": "хехе.ру"
  },
  {
    "id": "42277259",
    "Вакансия": "Python-разработчик",
    "Зарплата_нижний_порог": 160000.0,
    "Зарплата_верхний_порог": 200000.0,
    "Валюта": "руб.",
    "Ссылка": "https://nizhnekamsk.hh.ru/vacancy/42277259",
    "Сайт": "хехе.ру"
  },
  {
    "id": "43693023",
    "Вакансия": "Python / C++ разработчик",
    "Зарплата_нижний_порог": 150000.0,
    "Зарплата_верхний_порог": 230000.0,
    "Валюта": "руб.",
    "Ссылка": "https://nizhnekamsk.hh.ru/vacancy/43693023",
    "Сайт": "хехе.ру"
  },
  {
    "id": "30005963",
    "Вакансия": "Python developer",
    "Зарплата_нижний_порог": 4000.0,
    "Зарплата_верхний_порог": 0.0,
    "Валюта": "USD",
    "Ссылка": "https://nizhnekamsk.hh.ru/vacancy/30005963",
    "Сайт": "хехе.ру"
  },
  {
    "id": "43974138",
    "Вакансия": "Python Developer (USD Salary, Remote)",
    "Зарплата_нижний_порог": 250000.0,
    "Зарплата_верхний_порог": 350000.0,
    "Валюта": "руб.",
    "Ссылка": "https://nizhnekamsk.hh.ru/vacancy/43974138",
    "Сайт": "хехе.ру"
  },
  {
    "id": "37486302",
    "Вакансия": "Python разработчик",
    "Зарплата_нижний_порог": 150000.0,
    "Зарплата_верхний_порог": 250000.0,
    "Валюта": "руб.",
    "Ссылка": "https://nizhnekamsk.hh.ru/vacancy/37486302",
    "Сайт": "хехе.ру"
  },
  {
    "id": "41469811",
    "Вакансия": "Data Engineer",
    "Зарплата_нижний_порог": 250000.0,
    "Зарплата_верхний_порог": 0.0,
    "Валюта": "руб.",
    "Ссылка": "https://nizhnekamsk.hh.ru/vacancy/41469811",
    "Сайт": "хехе.ру"
  },
  {
    "id": "43835690",
    "Вакансия": "Разработчик Python / Django",
    "Зарплата_нижний_порог": 70000.0,
    "Зарплата_верхний_порог": 80000.0,
    "Валюта": "руб.",
    "Ссылка": "https://nizhnekamsk.hh.ru/vacancy/43835690",
    "Сайт": "хехе.ру"
  },
  {
    "id": "43282114",
    "Вакансия": "Разработчик Python",
    "Зарплата_нижний_порог": 180000.0,
    "Зарплата_верхний_порог": 0.0,
    "Валюта": "руб.",
    "Ссылка": "https://nizhnekamsk.hh.ru/vacancy/43282114",
    "Сайт": "хехе.ру"
  },
  {
    "id": "43289283",
    "Вакансия": "Data Scientist / Аналитик Data Science",
    "Зарплата_нижний_порог": 130000.0,
    "Зарплата_верхний_порог": 180000.0,
    "Валюта": "руб.",
    "Ссылка": "https://nizhnekamsk.hh.ru/vacancy/43289283",
    "Сайт": "хехе.ру"
  },
  {
    "id": "43825932",
    "Вакансия": "Junior Data Scientist",
    "Зарплата_нижний_порог": 120000.0,
    "Зарплата_верхний_порог": 0.0,
    "Валюта": "руб.",
    "Ссылка": "https://nizhnekamsk.hh.ru/vacancy/43825932",
    "Сайт": "хехе.ру"
  },
  {
    "id": "43941823",
    "Вакансия": "Программист Python",
    "Зарплата_нижний_порог": 0.0,
    "Зарплата_верхний_порог": 0.0,
    "Валюта": 0,
    "Ссылка": "https://nizhnekamsk.hh.ru/vacancy/43941823",
    "Сайт": "хехе.ру"
  },
  {
    "id": "43872229",
    "Вакансия": "Senior Python Developer (Django Rest framework+ Kubernetes) Product",
    "Зарплата_нижний_порог": 4000.0,
    "Зарплата_верхний_порог": 5000.0,
    "Валюта": "USD",
    "Ссылка": "https://nizhnekamsk.hh.ru/vacancy/43872229",
    "Сайт": "хехе.ру"
  },
  {
    "id": "43440824",
    "Вакансия": "Разработчик desktop приложений (Python)",
    "Зарплата_нижний_порог": 200000.0,
    "Зарплата_верхний_порог": 0.0,
    "Валюта": "руб.",
    "Ссылка": "https://nizhnekamsk.hh.ru/vacancy/43440824",
    "Сайт": "хехе.ру"
  },
  {
    "id": "43960362",
    "Вакансия": "Python (odoo) разработчик удаленно",
    "Зарплата_нижний_порог": 100000.0,
    "Зарплата_верхний_порог": 150000.0,
    "Валюта": "руб.",
    "Ссылка": "https://nizhnekamsk.hh.ru/vacancy/43960362",
    "Сайт": "хехе.ру"
  },
  {
    "id": "43377570",
    "Вакансия": "Junior Quantitative Researcher",
    "Зарплата_нижний_порог": 250000.0,
    "Зарплата_верхний_порог": 0.0,
    "Валюта": "руб.",
    "Ссылка": "https://nizhnekamsk.hh.ru/vacancy/43377570",
    "Сайт": "хехе.ру"
  },
  {
    "id": "43308988",
    "Вакансия": "Python разработчик (Django)",
    "Зарплата_нижний_порог": 100000.0,
    "Зарплата_верхний_порог": 0.0,
    "Валюта": "руб.",
    "Ссылка": "https://nizhnekamsk.hh.ru/vacancy/43308988",
    "Сайт": "хехе.ру"
  },
  {
    "id": "43927607",
    "Вакансия": "Разработчик Python",
    "Зарплата_нижний_порог": 0.0,
    "Зарплата_верхний_порог": 0.0,
    "Валюта": 0,
    "Ссылка": "https://nizhnekamsk.hh.ru/vacancy/43927607",
    "Сайт": "хехе.ру"
  },
  {
    "id": "43270626",
    "Вакансия": "Python Developer",
    "Зарплата_нижний_порог": 100000.0,
    "Зарплата_верхний_порог": 0.0,
    "Валюта": "руб.",
    "Ссылка": "https://nizhnekamsk.hh.ru/vacancy/43270626",
    "Сайт": "хехе.ру"
  },
  {
    "id": "43766255",
    "Вакансия": "Разработчик Python",
    "Зарплата_нижний_порог": 0.0,
    "Зарплата_верхний_порог": 0.0,
    "Валюта": 0,
    "Ссылка": "https://nizhnekamsk.hh.ru/vacancy/43766255",
    "Сайт": "хехе.ру"
  },
  {
    "id": "43766237",
    "Вакансия": "Data scientists, Младший (Junior)",
    "Зарплата_нижний_порог": 0.0,
    "Зарплата_верхний_порог": 0.0,
    "Валюта": 0,
    "Ссылка": "https://nizhnekamsk.hh.ru/vacancy/43766237",
    "Сайт": "хехе.ру"
  },
  {
    "id": "43608616",
    "Вакансия": "Data Scientist",
    "Зарплата_нижний_порог": 0.0,
    "Зарплата_верхний_порог": 0.0,
    "Валюта": 0,
    "Ссылка": "https://nizhnekamsk.hh.ru/vacancy/43608616",
    "Сайт": "хехе.ру"
  },
  {
    "id": "43951342",
    "Вакансия": "Python Developer в проект (Сфера: Crypto, Blockchain)",
    "Зарплата_нижний_порог": 150000.0,
    "Зарплата_верхний_порог": 250000.0,
    "Валюта": "руб.",
    "Ссылка": "https://nizhnekamsk.hh.ru/vacancy/43951342",
    "Сайт": "хехе.ру"
  },
  {
    "id": "43624444",
    "Вакансия": "Middle разработчик Python / Django (удалённо)",
    "Зарплата_нижний_порог": 60000.0,
    "Зарплата_верхний_порог": 120000.0,
    "Валюта": "руб.",
    "Ссылка": "https://nizhnekamsk.hh.ru/vacancy/43624444",
    "Сайт": "хехе.ру"
  },
  {
    "id": "43890805",
    "Вакансия": "Backend разработчик (Python)",
    "Зарплата_нижний_порог": 0.0,
    "Зарплата_верхний_порог": 0.0,
    "Валюта": 0,
    "Ссылка": "https://nizhnekamsk.hh.ru/vacancy/43890805",
    "Сайт": "хехе.ру"
  },
  {
    "id": "43351933",
    "Вакансия": "Python/Django Full Stack Developer (Middle-Senior)",
    "Зарплата_нижний_порог": 270000.0,
    "Зарплата_верхний_порог": 340000.0,
    "Валюта": "руб.",
    "Ссылка": "https://nizhnekamsk.hh.ru/vacancy/43351933",
    "Сайт": "хехе.ру"
  },
  {
    "id": "43471916",
    "Вакансия": "Data Scientist / Quantitative Researcher",
    "Зарплата_нижний_порог": 250000.0,
    "Зарплата_верхний_порог": 0.0,
    "Валюта": "руб.",
    "Ссылка": "https://nizhnekamsk.hh.ru/vacancy/43471916",
    "Сайт": "хехе.ру"
  },
  {
    "id": "43314180",
    "Вакансия": "Python developer",
    "Зарплата_нижний_порог": 180000.0,
    "Зарплата_верхний_порог": 230000.0,
    "Валюта": "руб.",
    "Ссылка": "https://nizhnekamsk.hh.ru/vacancy/43314180",
    "Сайт": "хехе.ру"
  },
  {
    "id": "43661388",
    "Вакансия": "Python Программист-разработчик",
    "Зарплата_нижний_порог": 0.0,
    "Зарплата_верхний_порог": 0.0,
    "Валюта": 0,
    "Ссылка": "https://nizhnekamsk.hh.ru/vacancy/43661388",
    "Сайт": "хехе.ру"
  },
  {
    "id": "43960049",
    "Вакансия": "Python Разработчик",
    "Зарплата_нижний_порог": 0.0,
    "Зарплата_верхний_порог": 0.0,
    "Валюта": 0,
    "Ссылка": "https://nizhnekamsk.hh.ru/vacancy/43960049",
    "Сайт": "хехе.ру"
  },
  {
    "id": "43079410",
    "Вакансия": "Python-разработчик (Пульс)",
    "Зарплата_нижний_порог": 0.0,
    "Зарплата_верхний_порог": 0.0,
    "Валюта": 0,
    "Ссылка": "https://nizhnekamsk.hh.ru/vacancy/43079410",
    "Сайт": "хехе.ру"
  },
  {
    "id": "43757805",
    "Вакансия": "Разработчик Big Data",
    "Зарплата_нижний_порог": 250000.0,
    "Зарплата_верхний_порог": 300000.0,
    "Валюта": "руб.",
    "Ссылка": "https://nizhnekamsk.hh.ru/vacancy/43757805",
    "Сайт": "хехе.ру"
  },
  {
    "id": "43609319",
    "Вакансия": "Python developer",
    "Зарплата_нижний_порог": 100000.0,
    "Зарплата_верхний_порог": 140000.0,
    "Валюта": "руб.",
    "Ссылка": "https://nizhnekamsk.hh.ru/vacancy/43609319",
    "Сайт": "хехе.ру"
  },
  {
    "id": "43124540",
    "Вакансия": "Python developer / Junior ML engineer",
    "Зарплата_нижний_порог": 0.0,
    "Зарплата_верхний_порог": 0.0,
    "Валюта": 0,
    "Ссылка": "https://nizhnekamsk.hh.ru/vacancy/43124540",
    "Сайт": "хехе.ру"
  },
  {
    "id": "43450877",
    "Вакансия": "Специалист по машинному обучению (Python, Machine learning)",
    "Зарплата_нижний_порог": 0.0,
    "Зарплата_верхний_порог": 140000.0,
    "Валюта": "руб.",
    "Ссылка": "https://nizhnekamsk.hh.ru/vacancy/43450877",
    "Сайт": "хехе.ру"
  },
  {
    "id": "43711132",
    "Вакансия": "Data Analyst",
    "Зарплата_нижний_порог": 70000.0,
    "Зарплата_верхний_порог": 100000.0,
    "Валюта": "руб.",
    "Ссылка": "https://nizhnekamsk.hh.ru/vacancy/43711132",
    "Сайт": "хехе.ру"
  },
  {
    "id": "43932937",
    "Вакансия": "Python-разработчик",
    "Зарплата_нижний_порог": 200000.0,
    "Зарплата_верхний_порог": 0.0,
    "Валюта": "руб.",
    "Ссылка": "https://nizhnekamsk.hh.ru/vacancy/43932937",
    "Сайт": "хехе.ру"
  },
  {
    "id": "43920673",
    "Вакансия": "Junior Data Analyst",
    "Зарплата_нижний_порог": 0.0,
    "Зарплата_верхний_порог": 0.0,
    "Валюта": 0,
    "Ссылка": "https://nizhnekamsk.hh.ru/vacancy/43920673",
    "Сайт": "хехе.ру"
  },
  {
    "id": "43371453",
    "Вакансия": "Middle Python Developer",
    "Зарплата_нижний_порог": 150000.0,
    "Зарплата_верхний_порог": 200000.0,
    "Валюта": "руб.",
    "Ссылка": "https://nizhnekamsk.hh.ru/vacancy/43371453",
    "Сайт": "хехе.ру"
  },
  {
    "id": "43963666",
    "Вакансия": "Python-разработчик (middle+)",
    "Зарплата_нижний_порог": 0.0,
    "Зарплата_верхний_порог": 0.0,
    "Валюта": 0,
    "Ссылка": "https://nizhnekamsk.hh.ru/vacancy/43963666",
    "Сайт": "хехе.ру"
  },
  {
    "id": "43703343",
    "Вакансия": "Junior Django Developer",
    "Зарплата_нижний_порог": 80000.0,
    "Зарплата_верхний_порог": 100000.0,
    "Валюта": "руб.",
    "Ссылка": "https://nizhnekamsk.hh.ru/vacancy/43703343",
    "Сайт": "хехе.ру"
  },
  {
    "id": "43075940",
    "Вакансия": "Разработчик Python",
    "Зарплата_нижний_порог": 120000.0,
    "Зарплата_верхний_порог": 220000.0,
    "Валюта": "руб.",
    "Ссылка": "https://nizhnekamsk.hh.ru/vacancy/43075940",
    "Сайт": "хехе.ру"
  },
  {
    "id": "41467833",
    "Вакансия": "Senior QA Automation Engineer (Python)",
    "Зарплата_нижний_порог": 300000.0,
    "Зарплата_верхний_порог": 0.0,
    "Валюта": "руб.",
    "Ссылка": "https://nizhnekamsk.hh.ru/vacancy/41467833",
    "Сайт": "хехе.ру"
  },
  {
    "id": "43838099",
    "Вакансия": "Python middle/senior разработчик",
    "Зарплата_нижний_порог": 0.0,
    "Зарплата_верхний_порог": 180000.0,
    "Валюта": "руб.",
    "Ссылка": "https://nizhnekamsk.hh.ru/vacancy/43838099",
    "Сайт": "хехе.ру"
  },
  {
    "id": "43961654",
    "Вакансия": "Python разработчик (middle/senior)",
    "Зарплата_нижний_порог": 0.0,
    "Зарплата_верхний_порог": 0.0,
    "Валюта": 0,
    "Ссылка": "https://nizhnekamsk.hh.ru/vacancy/43961654",
    "Сайт": "хехе.ру"
  },
  {
    "id": "42600063",
    "Вакансия": "Python разработчик",
    "Зарплата_нижний_порог": 170000.0,
    "Зарплата_верхний_порог": 0.0,
    "Валюта": "руб.",
    "Ссылка": "https://nizhnekamsk.hh.ru/vacancy/42600063",
    "Сайт": "хехе.ру"
  },
  {
    "id": "42633232",
    "Вакансия": "Python backend разработчик",
    "Зарплата_нижний_порог": 140000.0,
    "Зарплата_верхний_порог": 160000.0,
    "Валюта": "руб.",
    "Ссылка": "https://nizhnekamsk.hh.ru/vacancy/42633232",
    "Сайт": "хехе.ру"
  },
  {
    "id": "43354290",
    "Вакансия": "Ведущий аналитик данных / Data Scientist",
    "Зарплата_нижний_порог": 0.0,
    "Зарплата_верхний_порог": 300000.0,
    "Валюта": "руб.",
    "Ссылка": "https://nizhnekamsk.hh.ru/vacancy/43354290",
    "Сайт": "хехе.ру"
  },
  {
    "id": "43627174",
    "Вакансия": "Middle Python Backend developer",
    "Зарплата_нижний_порог": 90000.0,
    "Зарплата_верхний_порог": 160000.0,
    "Валюта": "руб.",
    "Ссылка": "https://nizhnekamsk.hh.ru/vacancy/43627174",
    "Сайт": "хехе.ру"
  },
  {
    "id": "43909211",
    "Вакансия": "Data Scientist",
    "Зарплата_нижний_порог": 0.0,
    "Зарплата_верхний_порог": 225000.0,
    "Валюта": "руб.",
    "Ссылка": "https://nizhnekamsk.hh.ru/vacancy/43909211",
    "Сайт": "хехе.ру"
  },
  {
    "id": "43184453",
    "Вакансия": "Backend-разработчик (Python)",
    "Зарплата_нижний_порог": 70000.0,
    "Зарплата_верхний_порог": 140000.0,
    "Валюта": "руб.",
    "Ссылка": "https://nizhnekamsk.hh.ru/vacancy/43184453",
    "Сайт": "хехе.ру"
  },
  {
    "id": "43118816",
    "Вакансия": "Python разработчик (middle +)",
    "Зарплата_нижний_порог": 0.0,
    "Зарплата_верхний_порог": 200000.0,
    "Валюта": "руб.",
    "Ссылка": "https://nizhnekamsk.hh.ru/vacancy/43118816",
    "Сайт": "хехе.ру"
  },
  {
    "id": "41095804",
    "Вакансия": "Бэк-энд разработчик (Python, SQL)",
    "Зарплата_нижний_порог": 100000.0,
    "Зарплата_верхний_порог": 160000.0,
    "Валюта": "руб.",
    "Ссылка": "https://nizhnekamsk.hh.ru/vacancy/41095804",
    "Сайт": "хехе.ру"
  },
  {
    "id": "43357165",
    "Вакансия": "Data Scientist / Data Engineer",
    "Зарплата_нижний_порог": 150000.0,
    "Зарплата_верхний_порог": 0.0,
    "Валюта": "руб.",
    "Ссылка": "https://nizhnekamsk.hh.ru/vacancy/43357165",
    "Сайт": "хехе.ру"
  },
  {
    "id": "43736412",
    "Вакансия": "Python middle developer",
    "Зарплата_нижний_порог": 100000.0,
    "Зарплата_верхний_порог": 150000.0,
    "Валюта": "руб.",
    "Ссылка": "https://nizhnekamsk.hh.ru/vacancy/43736412",
    "Сайт": "хехе.ру"
  },
  {
    "id": "43394113",
    "Вакансия": "Middle QA Automation Engineer (Python)",
    "Зарплата_нижний_порог": 180000.0,
    "Зарплата_верхний_порог": 250000.0,
    "Валюта": "руб.",
    "Ссылка": "https://nizhnekamsk.hh.ru/vacancy/43394113",
    "Сайт": "хехе.ру"
  },
  {
    "id": "43394792",
    "Вакансия": "Senior Python Developer",
    "Зарплата_нижний_порог": 150000.0,
    "Зарплата_верхний_порог": 0.0,
    "Валюта": "руб.",
    "Ссылка": "https://nizhnekamsk.hh.ru/vacancy/43394792",
    "Сайт": "хехе.ру"
  },
  {
    "id": "43724848",
    "Вакансия": "Computer Vision Engineer",
    "Зарплата_нижний_порог": 0.0,
    "Зарплата_верхний_порог": 0.0,
    "Валюта": 0,
    "Ссылка": "https://nizhnekamsk.hh.ru/vacancy/43724848",
    "Сайт": "хехе.ру"
  },
  {
    "id": "42890144",
    "Вакансия": "Python разработчик в отдел автоматизации (R&D)",
    "Зарплата_нижний_порог": 0.0,
    "Зарплата_верхний_порог": 0.0,
    "Валюта": 0,
    "Ссылка": "https://nizhnekamsk.hh.ru/vacancy/42890144",
    "Сайт": "хехе.ру"
  },
  {
    "id": "43828438",
    "Вакансия": "Python developer",
    "Зарплата_нижний_порог": 0.0,
    "Зарплата_верхний_порог": 220000.0,
    "Валюта": "руб.",
    "Ссылка": "https://nizhnekamsk.hh.ru/vacancy/43828438",
    "Сайт": "хехе.ру"
  },
  {
    "id": "43948065",
    "Вакансия": "Python/Go Developer",
    "Зарплата_нижний_порог": 0.0,
    "Зарплата_верхний_порог": 0.0,
    "Валюта": 0,
    "Ссылка": "https://nizhnekamsk.hh.ru/vacancy/43948065",
    "Сайт": "хехе.ру"
  },
  {
    "id": "43856428",
    "Вакансия": "Middle/Senior Python Developer",
    "Зарплата_нижний_порог": 130000.0,
    "Зарплата_верхний_порог": 220000.0,
    "Валюта": "руб.",
    "Ссылка": "https://nizhnekamsk.hh.ru/vacancy/43856428",
    "Сайт": "хехе.ру"
  },
  {
    "id": "43878741",
    "Вакансия": "Middle python-разработчик (aiohttp)",
    "Зарплата_нижний_порог": 0.0,
    "Зарплата_верхний_порог": 200000.0,
    "Валюта": "руб.",
    "Ссылка": "https://nizhnekamsk.hh.ru/vacancy/43878741",
    "Сайт": "хехе.ру"
  },
  {
    "id": "43036692",
    "Вакансия": "Разработчик Python",
    "Зарплата_нижний_порог": 0.0,
    "Зарплата_верхний_порог": 150000.0,
    "Валюта": "руб.",
    "Ссылка": "https://nizhnekamsk.hh.ru/vacancy/43036692",
    "Сайт": "хехе.ру"
  },
  {
    "id": "43623428",
    "Вакансия": "Python разработчик",
    "Зарплата_нижний_порог": 50000.0,
    "Зарплата_верхний_порог": 0.0,
    "Валюта": "руб.",
    "Ссылка": "https://nizhnekamsk.hh.ru/vacancy/43623428",
    "Сайт": "хехе.ру"
  },
  {
    "id": "43600944",
    "Вакансия": "Программист Python/Бизнес-аналитик",
    "Зарплата_нижний_порог": 0.0,
    "Зарплата_верхний_порог": 0.0,
    "Валюта": 0,
    "Ссылка": "https://nizhnekamsk.hh.ru/vacancy/43600944",
    "Сайт": "хехе.ру"
  },
  {
    "id": "43850455",
    "Вакансия": "Data Engineer (Python)",
    "Зарплата_нижний_порог": 0.0,
    "Зарплата_верхний_порог": 0.0,
    "Валюта": 0,
    "Ссылка": "https://nizhnekamsk.hh.ru/vacancy/43850455",
    "Сайт": "хехе.ру"
  },
  {
    "id": "43931532",
    "Вакансия": "Python/Django Web Developer",
    "Зарплата_нижний_порог": 4000.0,
    "Зарплата_верхний_порог": 6000.0,
    "Валюта": "USD",
    "Ссылка": "https://nizhnekamsk.hh.ru/vacancy/43931532",
    "Сайт": "хехе.ру"
  },
  {
    "id": "42399463",
    "Вакансия": "Back-end Developer(C++ и Python).",
    "Зарплата_нижний_порог": 0.0,
    "Зарплата_верхний_порог": 0.0,
    "Валюта": 0,
    "Ссылка": "https://nizhnekamsk.hh.ru/vacancy/42399463",
    "Сайт": "хехе.ру"
  },
  {
    "id": "43926397",
    "Вакансия": "Software Developer Python",
    "Зарплата_нижний_порог": 50000.0,
    "Зарплата_верхний_порог": 120000.0,
    "Валюта": "руб.",
    "Ссылка": "https://nizhnekamsk.hh.ru/vacancy/43926397",
    "Сайт": "хехе.ру"
  },
  {
    "id": "43280019",
    "Вакансия": "Middle Python разработчик",
    "Зарплата_нижний_порог": 0.0,
    "Зарплата_верхний_порог": 0.0,
    "Валюта": 0,
    "Ссылка": "https://nizhnekamsk.hh.ru/vacancy/43280019",
    "Сайт": "хехе.ру"
  },
  {
    "id": "43520619",
    "Вакансия": "Senior Python Developer",
    "Зарплата_нижний_порог": 0.0,
    "Зарплата_верхний_порог": 0.0,
    "Валюта": 0,
    "Ссылка": "https://nizhnekamsk.hh.ru/vacancy/43520619",
    "Сайт": "хехе.ру"
  },
  {
    "id": "43959754",
    "Вакансия": "Старший инженер в области машинного обучения (Senior Data Scientist)",
    "Зарплата_нижний_порог": 0.0,
    "Зарплата_верхний_порог": 200000.0,
    "Валюта": "руб.",
    "Ссылка": "https://nizhnekamsk.hh.ru/vacancy/43959754",
    "Сайт": "хехе.ру"
  },
  {
    "id": "43471488",
    "Вакансия": "Разработчик Python для поддержки рефакторинга легаси кода",
    "Зарплата_нижний_порог": 100000.0,
    "Зарплата_верхний_порог": 200000.0,
    "Валюта": "руб.",
    "Ссылка": "https://nizhnekamsk.hh.ru/vacancy/43471488",
    "Сайт": "хехе.ру"
  },
  {
    "id": "43435041",
    "Вакансия": "Программист Python (ML)",
    "Зарплата_нижний_порог": 0.0,
    "Зарплата_верхний_порог": 0.0,
    "Валюта": 0,
    "Ссылка": "https://nizhnekamsk.hh.ru/vacancy/43435041",
    "Сайт": "хехе.ру"
  },
  {
    "id": "43623872",
    "Вакансия": "Backend разработчик (Python)",
    "Зарплата_нижний_порог": 160000.0,
    "Зарплата_верхний_порог": 0.0,
    "Валюта": "руб.",
    "Ссылка": "https://nizhnekamsk.hh.ru/vacancy/43623872",
    "Сайт": "хехе.ру"
  },
  {
    "id": "43623437",
    "Вакансия": "Python (Django) разработчик",
    "Зарплата_нижний_порог": 50000.0,
    "Зарплата_верхний_порог": 0.0,
    "Валюта": "руб.",
    "Ссылка": "https://nizhnekamsk.hh.ru/vacancy/43623437",
    "Сайт": "хехе.ру"
  },
  {
    "id": "43512073",
    "Вакансия": "Python + Go разработчик (можно удаленно)",
    "Зарплата_нижний_порог": 150000.0,
    "Зарплата_верхний_порог": 220000.0,
    "Валюта": "руб.",
    "Ссылка": "https://nizhnekamsk.hh.ru/vacancy/43512073",
    "Сайт": "хехе.ру"
  },
  {
    "id": "43686427",
    "Вакансия": "ML - разработчик / Data Scientist",
    "Зарплата_нижний_порог": 0.0,
    "Зарплата_верхний_порог": 230000.0,
    "Валюта": "руб.",
    "Ссылка": "https://nizhnekamsk.hh.ru/vacancy/43686427",
    "Сайт": "хехе.ру"
  },
  {
    "id": "43817671",
    "Вакансия": "QA Automation Engineer (Python), remote",
    "Зарплата_нижний_порог": 1500.0,
    "Зарплата_верхний_порог": 2000.0,
    "Валюта": "USD",
    "Ссылка": "https://nizhnekamsk.hh.ru/vacancy/43817671",
    "Сайт": "хехе.ру"
  },
  {
    "id": "43068966",
    "Вакансия": "Разработчик Python",
    "Зарплата_нижний_порог": 0.0,
    "Зарплата_верхний_порог": 0.0,
    "Валюта": 0,
    "Ссылка": "https://nizhnekamsk.hh.ru/vacancy/43068966",
    "Сайт": "хехе.ру"
  },
  {
    "id": "42165443",
    "Вакансия": "Python-разработчик (Middle)",
    "Зарплата_нижний_порог": 0.0,
    "Зарплата_верхний_порог": 220000.0,
    "Валюта": "руб.",
    "Ссылка": "https://nizhnekamsk.hh.ru/vacancy/42165443",
    "Сайт": "хехе.ру"
  },
  {
    "id": "43298031",
    "Вакансия": "Senior/Middle backend-разработчик (Python, Django)",
    "Зарплата_нижний_порог": 150000.0,
    "Зарплата_верхний_порог": 230000.0,
    "Валюта": "руб.",
    "Ссылка": "https://nizhnekamsk.hh.ru/vacancy/43298031",
    "Сайт": "хехе.ру"
  },
  {
    "id": "43552870",
    "Вакансия": "Python Backend Developer (Middle)",
    "Зарплата_нижний_порог": 0.0,
    "Зарплата_верхний_порог": 200000.0,
    "Валюта": "руб.",
    "Ссылка": "https://nizhnekamsk.hh.ru/vacancy/43552870",
    "Сайт": "хехе.ру"
  },
  {
    "id": "43948394",
    "Вакансия": "Middle\\senior python developer",
    "Зарплата_нижний_порог": 0.0,
    "Зарплата_верхний_порог": 0.0,
    "Валюта": 0,
    "Ссылка": "https://nizhnekamsk.hh.ru/vacancy/43948394",
    "Сайт": "хехе.ру"
  },
  {
    "id": "42631058",
    "Вакансия": "Web-разработчик (React, Python)",
    "Зарплата_нижний_порог": 800.0,
    "Зарплата_верхний_порог": 3000.0,
    "Валюта": "USD",
    "Ссылка": "https://nizhnekamsk.hh.ru/vacancy/42631058",
    "Сайт": "хехе.ру"
  },
  {
    "id": "40041376",
    "Вакансия": "Разработчик / Инженер-программист (Python)",
    "Зарплата_нижний_порог": 0.0,
    "Зарплата_верхний_порог": 230000.0,
    "Валюта": "руб.",
    "Ссылка": "https://nizhnekamsk.hh.ru/vacancy/40041376",
    "Сайт": "хехе.ру"
  },
  {
    "id": "37430732",
    "Вакансия": "Pyth‎on Developer",
    "Зарплата_нижний_порог": 0.0,
    "Зарплата_верхний_порог": 0.0,
    "Валюта": 0,
    "Ссылка": "https://nizhnekamsk.hh.ru/vacancy/37430732",
    "Сайт": "хехе.ру"
  },
  {
    "id": "43188984",
    "Вакансия": "Data Scientist",
    "Зарплата_нижний_порог": 0.0,
    "Зарплата_верхний_порог": 0.0,
    "Валюта": 0,
    "Ссылка": "https://nizhnekamsk.hh.ru/vacancy/43188984",
    "Сайт": "хехе.ру"
  },
  {
    "id": "41785083",
    "Вакансия": "Python Developer (PIM)",
    "Зарплата_нижний_порог": 0.0,
    "Зарплата_верхний_порог": 0.0,
    "Валюта": 0,
    "Ссылка": "https://nizhnekamsk.hh.ru/vacancy/41785083",
    "Сайт": "хехе.ру"
  },
  {
    "id": "43734534",
    "Вакансия": "Аналитик / Data Analyst",
    "Зарплата_нижний_порог": 0.0,
    "Зарплата_верхний_порог": 0.0,
    "Валюта": 0,
    "Ссылка": "https://nizhnekamsk.hh.ru/vacancy/43734534",
    "Сайт": "хехе.ру"
  },
  {
    "id": "43959987",
    "Вакансия": "Quantitative Research / Data Science Intern",
    "Зарплата_нижний_порог": 0.0,
    "Зарплата_верхний_порог": 0.0,
    "Валюта": 0,
    "Ссылка": "https://nizhnekamsk.hh.ru/vacancy/43959987",
    "Сайт": "хехе.ру"
  },
  {
    "id": "43265056",
    "Вакансия": "Программист Python",
    "Зарплата_нижний_порог": 0.0,
    "Зарплата_верхний_порог": 170000.0,
    "Валюта": "руб.",
    "Ссылка": "https://nizhnekamsk.hh.ru/vacancy/43265056",
    "Сайт": "хехе.ру"
  },
  {
    "id": "43688553",
    "Вакансия": "Python разработчик",
    "Зарплата_нижний_порог": 0.0,
    "Зарплата_верхний_порог": 0.0,
    "Валюта": 0,
    "Ссылка": "https://nizhnekamsk.hh.ru/vacancy/43688553",
    "Сайт": "хехе.ру"
  },
  {
    "id": "42683816",
    "Вакансия": "Data Scientist",
    "Зарплата_нижний_порог": 180000.0,
    "Зарплата_верхний_порог": 250000.0,
    "Валюта": "руб.",
    "Ссылка": "https://nizhnekamsk.hh.ru/vacancy/42683816",
    "Сайт": "хехе.ру"
  },
  {
    "id": "41926085",
    "Вакансия": "Разработчик (Python)",
    "Зарплата_нижний_порог": 0.0,
    "Зарплата_верхний_порог": 0.0,
    "Валюта": 0,
    "Ссылка": "https://nizhnekamsk.hh.ru/vacancy/41926085",
    "Сайт": "хехе.ру"
  },
  {
    "id": "43896048",
    "Вакансия": "Python Developer (New Product)",
    "Зарплата_нижний_порог": 0.0,
    "Зарплата_верхний_порог": 0.0,
    "Валюта": 0,
    "Ссылка": "https://nizhnekamsk.hh.ru/vacancy/43896048",
    "Сайт": "хехе.ру"
  },
  {
    "id": "40777213",
    "Вакансия": "Python/Go разработчик",
    "Зарплата_нижний_порог": 0.0,
    "Зарплата_верхний_порог": 0.0,
    "Валюта": 0,
    "Ссылка": "https://nizhnekamsk.hh.ru/vacancy/40777213",
    "Сайт": "хехе.ру"
  },
  {
    "id": "43712987",
    "Вакансия": "Разработчик Python",
    "Зарплата_нижний_порог": 0.0,
    "Зарплата_верхний_порог": 0.0,
    "Валюта": 0,
    "Ссылка": "https://nizhnekamsk.hh.ru/vacancy/43712987",
    "Сайт": "хехе.ру"
  },
  {
    "id": "35871016",
    "Вакансия": "Разработчик Python",
    "Зарплата_нижний_порог": 0.0,
    "Зарплата_верхний_порог": 0.0,
    "Валюта": 0,
    "Ссылка": "https://nizhnekamsk.hh.ru/vacancy/35871016",
    "Сайт": "хехе.ру"
  },
  {
    "id": "41019318",
    "Вакансия": "Python разработчик (SberDevices)",
    "Зарплата_нижний_порог": 0.0,
    "Зарплата_верхний_порог": 0.0,
    "Валюта": 0,
    "Ссылка": "https://nizhnekamsk.hh.ru/vacancy/41019318",
    "Сайт": "хехе.ру"
  },
  {
    "id": "42934122",
    "Вакансия": "Middle/Senior Python developer",
    "Зарплата_нижний_порог": 120000.0,
    "Зарплата_верхний_порог": 200000.0,
    "Валюта": "руб.",
    "Ссылка": "https://nizhnekamsk.hh.ru/vacancy/42934122",
    "Сайт": "хехе.ру"
  },
  {
    "id": "43269339",
    "Вакансия": "Data Scientist (middle)",
    "Зарплата_нижний_порог": 0.0,
    "Зарплата_верхний_порог": 180000.0,
    "Валюта": "руб.",
    "Ссылка": "https://nizhnekamsk.hh.ru/vacancy/43269339",
    "Сайт": "хехе.ру"
  },
  {
    "id": "43272495",
    "Вакансия": "Web-разработчик fullstack (python+javascript)",
    "Зарплата_нижний_порог": 50000.0,
    "Зарплата_верхний_порог": 150000.0,
    "Валюта": "руб.",
    "Ссылка": "https://nizhnekamsk.hh.ru/vacancy/43272495",
    "Сайт": "хехе.ру"
  },
  {
    "id": "43735860",
    "Вакансия": "Python developer",
    "Зарплата_нижний_порог": 0.0,
    "Зарплата_верхний_порог": 0.0,
    "Валюта": 0,
    "Ссылка": "https://nizhnekamsk.hh.ru/vacancy/43735860",
    "Сайт": "хехе.ру"
  },
  {
    "id": "43357572",
    "Вакансия": "Python разработчик в команду Видеосмотрения",
    "Зарплата_нижний_порог": 0.0,
    "Зарплата_верхний_порог": 250000.0,
    "Валюта": "руб.",
    "Ссылка": "https://nizhnekamsk.hh.ru/vacancy/43357572",
    "Сайт": "хехе.ру"
  },
  {
    "id": "43379499",
    "Вакансия": "Разработчик Python",
    "Зарплата_нижний_порог": 0.0,
    "Зарплата_верхний_порог": 0.0,
    "Валюта": 0,
    "Ссылка": "https://nizhnekamsk.hh.ru/vacancy/43379499",
    "Сайт": "хехе.ру"
  },
  {
    "id": "43146283",
    "Вакансия": "Data Science разработчик (NLP), middle",
    "Зарплата_нижний_порог": 150000.0,
    "Зарплата_верхний_порог": 0.0,
    "Валюта": "руб.",
    "Ссылка": "https://nizhnekamsk.hh.ru/vacancy/43146283",
    "Сайт": "хехе.ру"
  },
  {
    "id": "43343275",
    "Вакансия": "Разработчик Python",
    "Зарплата_нижний_порог": 0.0,
    "Зарплата_верхний_порог": 200000.0,
    "Валюта": "руб.",
    "Ссылка": "https://nizhnekamsk.hh.ru/vacancy/43343275",
    "Сайт": "хехе.ру"
  },
  {
    "id": "43689312",
    "Вакансия": "Python разработчик / Программист Python / Python developer",
    "Зарплата_нижний_порог": 0.0,
    "Зарплата_верхний_порог": 0.0,
    "Валюта": 0,
    "Ссылка": "https://nizhnekamsk.hh.ru/vacancy/43689312",
    "Сайт": "хехе.ру"
  },
  {
    "id": "43702705",
    "Вакансия": "Разработчик Python (Middle)",
    "Зарплата_нижний_порог": 120000.0,
    "Зарплата_верхний_порог": 150000.0,
    "Валюта": "руб.",
    "Ссылка": "https://nizhnekamsk.hh.ru/vacancy/43702705",
    "Сайт": "хехе.ру"
  },
  {
    "id": "43619688",
    "Вакансия": "Python-разработчик",
    "Зарплата_нижний_порог": 0.0,
    "Зарплата_верхний_порог": 0.0,
    "Валюта": 0,
    "Ссылка": "https://nizhnekamsk.hh.ru/vacancy/43619688",
    "Сайт": "хехе.ру"
  },
  {
    "id": "42547797",
    "Вакансия": "Старший разработчик (Python)",
    "Зарплата_нижний_порог": 160000.0,
    "Зарплата_верхний_порог": 190000.0,
    "Валюта": "руб.",
    "Ссылка": "https://nizhnekamsk.hh.ru/vacancy/42547797",
    "Сайт": "хехе.ру"
  },
  {
    "id": "42305410",
    "Вакансия": "Backend Python Developer (MTS AI)",
    "Зарплата_нижний_порог": 0.0,
    "Зарплата_верхний_порог": 0.0,
    "Валюта": 0,
    "Ссылка": "https://nizhnekamsk.hh.ru/vacancy/42305410",
    "Сайт": "хехе.ру"
  },
  {
    "id": "43926854",
    "Вакансия": "Python Team Lead",
    "Зарплата_нижний_порог": 0.0,
    "Зарплата_верхний_порог": 0.0,
    "Валюта": 0,
    "Ссылка": "https://nizhnekamsk.hh.ru/vacancy/43926854",
    "Сайт": "хехе.ру"
  },
  {
    "id": "43931254",
    "Вакансия": "Python developer (Python+Apache Airflow)",
    "Зарплата_нижний_порог": 0.0,
    "Зарплата_верхний_порог": 0.0,
    "Валюта": 0,
    "Ссылка": "https://nizhnekamsk.hh.ru/vacancy/43931254",
    "Сайт": "хехе.ру"
  },
  {
    "id": "43616869",
    "Вакансия": "AI разработчик",
    "Зарплата_нижний_порог": 70000.0,
    "Зарплата_верхний_порог": 100000.0,
    "Валюта": "руб.",
    "Ссылка": "https://nizhnekamsk.hh.ru/vacancy/43616869",
    "Сайт": "хехе.ру"
  },
  {
    "id": "43809736",
    "Вакансия": "Data scientist/Бизнес-аналитик (Junior/Middle) в консалтинг",
    "Зарплата_нижний_порог": 0.0,
    "Зарплата_верхний_порог": 0.0,
    "Валюта": 0,
    "Ссылка": "https://nizhnekamsk.hh.ru/vacancy/43809736",
    "Сайт": "хехе.ру"
  },
  {
    "id": "43889597",
    "Вакансия": "Python разработчик (django)",
    "Зарплата_нижний_порог": 0.0,
    "Зарплата_верхний_порог": 350000.0,
    "Валюта": "руб.",
    "Ссылка": "https://nizhnekamsk.hh.ru/vacancy/43889597",
    "Сайт": "хехе.ру"
  },
  {
    "id": "39416083",
    "Вакансия": "Data scientist",
    "Зарплата_нижний_порог": 0.0,
    "Зарплата_верхний_порог": 0.0,
    "Валюта": 0,
    "Ссылка": "https://nizhnekamsk.hh.ru/vacancy/39416083",
    "Сайт": "хехе.ру"
  },
  {
    "id": "42967899",
    "Вакансия": "Старший Python + Go разработчик",
    "Зарплата_нижний_порог": 0.0,
    "Зарплата_верхний_порог": 250000.0,
    "Валюта": "руб.",
    "Ссылка": "https://nizhnekamsk.hh.ru/vacancy/42967899",
    "Сайт": "хехе.ру"
  },
  {
    "id": "40942389",
    "Вакансия": "Python программист",
    "Зарплата_нижний_порог": 0.0,
    "Зарплата_верхний_порог": 0.0,
    "Валюта": 0,
    "Ссылка": "https://nizhnekamsk.hh.ru/vacancy/40942389",
    "Сайт": "хехе.ру"
  },
  {
    "id": "42747875",
    "Вакансия": "Full Stack Web Developer (Python)",
    "Зарплата_нижний_порог": 0.0,
    "Зарплата_верхний_порог": 0.0,
    "Валюта": 0,
    "Ссылка": "https://nizhnekamsk.hh.ru/vacancy/42747875",
    "Сайт": "хехе.ру"
  },
  {
    "id": "43627028",
    "Вакансия": "Middle / Senior Django разработчик (удаленка)",
    "Зарплата_нижний_порог": 70000.0,
    "Зарплата_верхний_порог": 175000.0,
    "Валюта": "руб.",
    "Ссылка": "https://nizhnekamsk.hh.ru/vacancy/43627028",
    "Сайт": "хехе.ру"
  },
  {
    "id": "41975139",
    "Вакансия": "Machine Learning Researcher (Senior)",
    "Зарплата_нижний_порог": 0.0,
    "Зарплата_верхний_порог": 0.0,
    "Валюта": 0,
    "Ссылка": "https://nizhnekamsk.hh.ru/vacancy/41975139",
    "Сайт": "хехе.ру"
  },
  {
    "id": "43372642",
    "Вакансия": "Senior Python backend developer",
    "Зарплата_нижний_порог": 0.0,
    "Зарплата_верхний_порог": 0.0,
    "Валюта": 0,
    "Ссылка": "https://nizhnekamsk.hh.ru/vacancy/43372642",
    "Сайт": "хехе.ру"
  },
  {
    "id": "43925937",
    "Вакансия": "Senior Python-разработчик",
    "Зарплата_нижний_порог": 200000.0,
    "Зарплата_верхний_порог": 0.0,
    "Валюта": "руб.",
    "Ссылка": "https://nizhnekamsk.hh.ru/vacancy/43925937",
    "Сайт": "хехе.ру"
  }
]